poynt/__init__.py
poynt/api.py
poynt/business.py
poynt/business_application.py
poynt/businessuser.py
poynt/catalog.py
poynt/cloudmessage.py
poynt/customer.py
poynt/helpers.py
poynt/hook.py
poynt/order.py
poynt/product.py
poynt/report.py
poynt/store.py
poynt/tax.py
poynt/transaction.py
poynt-0.0.16.dist-info/LICENSE
poynt-0.0.16.dist-info/METADATA
poynt-0.0.16.dist-info/WHEEL
poynt-0.0.16.dist-info/top_level.txt
poynt-0.0.16.dist-info/RECORD
