Metadata-Version: 2.1
Name: poynt
Version: 0.0.16
Summary: The official Poynt Python SDK.
Home-page: https://github.com/poynt/poynt-python
Author: Charles Feng
Author-email: c@poynt.com
License: MIT
Platform: UNKNOWN
Classifier: Development Status :: 5 - Production/Stable
Classifier: Intended Audience :: Developers
Classifier: License :: OSI Approved :: MIT License
Classifier: Operating System :: OS Independent
Classifier: Programming Language :: Python
Classifier: Programming Language :: Python :: 2.6
Classifier: Programming Language :: Python :: 2.7
Classifier: Programming Language :: Python :: 3.3
Classifier: Programming Language :: Python :: 3.4
Classifier: Programming Language :: Python :: 3.5
Classifier: Topic :: Software Development :: Libraries :: Python Modules
Requires-Dist: requests
Requires-Dist: pyjwt
